[
  {
    "date": "2023-07-24",
    "open": 130.309998,
    "high": 131.660004,
    "low": 128.350006,
    "close": 128.800003,
    "adjClose": 128.800003,
    "volume": 45591100
  },
  {
    "date": "2023-07-25",
    "open": 129.309998,
    "high": 129.580002,
    "low": 128.529999,
    "close": 129.130005,
    "adjClose": 129.130005,
    "volume": 39236700
  },
  {
    "date": "2023-07-26",
    "open": 126.510002,
    "high": 129.080002,
    "low": 126.110001,
    "close": 128.149994,
    "adjClose": 128.149994,
    "volume": 53910100
  },
  {
    "date": "2023-07-27",
    "open": 131.0,
    "high": 132.630005,
    "low": 127.790001,
    "close": 128.25,
    "adjClose": 128.25,
    "volume": 52610700
  },
  {
    "date": "2023-07-28",
    "open": 129.690002,
    "high": 133.009995,
    "low": 129.330002,
    "close": 132.210007,
    "adjClose": 132.210007,
    "volume": 46317400
  },
  {
    "date": "2023-07-31",
    "open": 133.199997,
    "high": 133.869995,
    "low": 132.380005,
    "close": 133.679993,
    "adjClose": 133.679993,
    "volume": 41901500
  },
  {
    "date": "2023-08-01",
    "open": 133.550003,
    "high": 133.690002,
    "low": 131.619995,
    "close": 131.690002,
    "adjClose": 131.690002,
    "volume": 42098500
  },
  {
    "date": "2023-08-02",
    "open": 130.149994,
    "high": 130.229996,
    "low": 126.82,
    "close": 128.210007,
    "adjClose": 128.210007,
    "volume": 51027600
  },
  {
    "date": "2023-08-03",
    "open": 127.480003,
    "high": 129.839996,
    "low": 126.410004,
    "close": 128.910004,
    "adjClose": 128.910004,
    "volume": 88585200
  },
  {
    "date": "2023-08-04",
    "open": 141.059998,
    "high": 143.630005,
    "low": 139.320007,
    "close": 139.570007,
    "adjClose": 139.570007,
    "volume": 152938700
  },
  {
    "date": "2023-08-07",
    "open": 140.990005,
    "high": 142.539993,
    "low": 138.949997,
    "close": 142.220001,
    "adjClose": 142.220001,
    "volume": 71213100
  },
  {
    "date": "2023-08-08",
    "open": 140.619995,
    "high": 140.839996,
    "low": 138.419998,
    "close": 139.940002,
    "adjClose": 139.940002,
    "volume": 51710500
  },
  {
    "date": "2023-08-09",
    "open": 139.970001,
    "high": 140.320007,
    "low": 137.100006,
    "close": 137.850006,
    "adjClose": 137.850006,
    "volume": 50017300
  },
  {
    "date": "2023-08-10",
    "open": 139.070007,
    "high": 140.410004,
    "low": 137.490005,
    "close": 138.559998,
    "adjClose": 138.559998,
    "volume": 58928400
  },
  {
    "date": "2023-08-11",
    "open": 137.399994,
    "high": 139.330002,
    "low": 137.0,
    "close": 138.410004,
    "adjClose": 138.410004,
    "volume": 42832100
  },
  {
    "date": "2023-08-14",
    "open": 138.300003,
    "high": 140.589996,
    "low": 137.75,
    "close": 140.570007,
    "adjClose": 140.570007,
    "volume": 47148700
  },
  {
    "date": "2023-08-15",
    "open": 140.050003,
    "high": 141.279999,
    "low": 137.229996,
    "close": 137.669998,
    "adjClose": 137.669998,
    "volume": 42781500
  },
  {
    "date": "2023-08-16",
    "open": 137.190002,
    "high": 137.270004,
    "low": 135.009995,
    "close": 135.070007,
    "adjClose": 135.070007,
    "volume": 41675900
  },
  {
    "date": "2023-08-17",
    "open": 135.460007,
    "high": 136.089996,
    "low": 133.529999,
    "close": 133.979996,
    "adjClose": 133.979996,
    "volume": 48354100
  },
  {
    "date": "2023-08-18",
    "open": 131.619995,
    "high": 134.070007,
    "low": 131.149994,
    "close": 133.220001,
    "adjClose": 133.220001,
    "volume": 48469400
  },
  {
    "date": "2023-08-21",
    "open": 133.740005,
    "high": 135.190002,
    "low": 132.710007,
    "close": 134.679993,
    "adjClose": 134.679993,
    "volume": 41442500
  },
  {
    "date": "2023-08-22",
    "open": 135.080002,
    "high": 135.649994,
    "low": 133.729996,
    "close": 134.25,
    "adjClose": 134.25,
    "volume": 32935100
  },
  {
    "date": "2023-08-23",
    "open": 134.5,
    "high": 135.949997,
    "low": 133.220001,
    "close": 135.520004,
    "adjClose": 135.520004,
    "volume": 42801000
  },
  {
    "date": "2023-08-24",
    "open": 136.399994,
    "high": 136.779999,
    "low": 131.830002,
    "close": 131.839996,
    "adjClose": 131.839996,
    "volume": 43646300
  },
  {
    "date": "2023-08-25",
    "open": 132.470001,
    "high": 133.869995,
    "low": 130.580002,
    "close": 133.259995,
    "adjClose": 133.259995,
    "volume": 44147500
  },
  {
    "date": "2023-08-28",
    "open": 133.779999,
    "high": 133.949997,
    "low": 131.850006,
    "close": 133.139999,
    "adjClose": 133.139999,
    "volume": 34108400
  },
  {
    "date": "2023-08-29",
    "open": 133.380005,
    "high": 135.139999,
    "low": 133.25,
    "close": 134.910004,
    "adjClose": 134.910004,
    "volume": 38646100
  },
  {
    "date": "2023-08-30",
    "open": 134.929993,
    "high": 135.679993,
    "low": 133.919998,
    "close": 135.070007,
    "adjClose": 135.070007,
    "volume": 36137000
  },
  {
    "date": "2023-08-31",
    "open": 135.059998,
    "high": 138.789993,
    "low": 135.0,
    "close": 138.009995,
    "adjClose": 138.009995,
    "volume": 58781300
  },
  {
    "date": "2023-09-01",
    "open": 139.460007,
    "high": 139.960007,
    "low": 136.880005,
    "close": 138.119995,
    "adjClose": 138.119995,
    "volume": 40948300
  },
  {
    "date": "2023-09-05",
    "open": 137.729996,
    "high": 137.800003,
    "low": 135.820007,
    "close": 137.270004,
    "adjClose": 137.270004,
    "volume": 40636700
  },
  {
    "date": "2023-09-06",
    "open": 136.320007,
    "high": 137.449997,
    "low": 134.610001,
    "close": 135.360001,
    "adjClose": 135.360001,
    "volume": 41785500
  },
  {
    "date": "2023-09-07",
    "open": 133.899994,
    "high": 138.029999,
    "low": 133.160004,
    "close": 137.850006,
    "adjClose": 137.850006,
    "volume": 48498900
  },
  {
    "date": "2023-09-08",
    "open": 136.860001,
    "high": 138.850006,
    "low": 136.75,
    "close": 138.229996,
    "adjClose": 138.229996,
    "volume": 38348200
  },
  {
    "date": "2023-09-11",
    "open": 138.75,
    "high": 143.619995,
    "low": 138.639999,
    "close": 143.100006,
    "adjClose": 143.100006,
    "volume": 56764500
  },
  {
    "date": "2023-09-12",
    "open": 142.320007,
    "high": 143.0,
    "low": 140.610001,
    "close": 141.229996,
    "adjClose": 141.229996,
    "volume": 42668500
  },
  {
    "date": "2023-09-13",
    "open": 140.949997,
    "high": 144.979996,
    "low": 140.869995,
    "close": 144.850006,
    "adjClose": 144.850006,
    "volume": 60465200
  },
  {
    "date": "2023-09-14",
    "open": 145.080002,
    "high": 145.860001,
    "low": 142.949997,
    "close": 144.720001,
    "adjClose": 144.720001,
    "volume": 64033600
  },
  {
    "date": "2023-09-15",
    "open": 142.690002,
    "high": 143.570007,
    "low": 140.089996,
    "close": 140.389999,
    "adjClose": 140.389999,
    "volume": 102861700
  },
  {
    "date": "2023-09-18",
    "open": 140.479996,
    "high": 141.75,
    "low": 139.220001,
    "close": 139.979996,
    "adjClose": 139.979996,
    "volume": 42823500
  },
  {
    "date": "2023-09-19",
    "open": 138.699997,
    "high": 138.839996,
    "low": 135.559998,
    "close": 137.630005,
    "adjClose": 137.630005,
    "volume": 61482500
  },
  {
    "date": "2023-09-20",
    "open": 138.550003,
    "high": 139.369995,
    "low": 135.199997,
    "close": 135.289993,
    "adjClose": 135.289993,
    "volume": 46263700
  },
  {
    "date": "2023-09-21",
    "open": 131.940002,
    "high": 132.240005,
    "low": 129.309998,
    "close": 129.330002,
    "adjClose": 129.330002,
    "volume": 70234800
  },
  {
    "date": "2023-09-22",
    "open": 131.110001,
    "high": 132.029999,
    "low": 128.520004,
    "close": 129.119995,
    "adjClose": 129.119995,
    "volume": 59904300
  },
  {
    "date": "2023-09-25",
    "open": 129.360001,
    "high": 131.779999,
    "low": 128.770004,
    "close": 131.270004,
    "adjClose": 131.270004,
    "volume": 46017800
  },
  {
    "date": "2023-09-26",
    "open": 130.119995,
    "high": 130.389999,
    "low": 125.279999,
    "close": 125.980003,
    "adjClose": 125.980003,
    "volume": 73048200
  },
  {
    "date": "2023-09-27",
    "open": 125.760002,
    "high": 127.480003,
    "low": 124.129997,
    "close": 125.980003,
    "adjClose": 125.980003,
    "volume": 66553400
  },
  {
    "date": "2023-09-28",
    "open": 124.040001,
    "high": 126.580002,
    "low": 123.040001,
    "close": 125.980003,
    "adjClose": 125.980003,
    "volume": 54555000
  },
  {
    "date": "2023-09-29",
    "open": 128.199997,
    "high": 129.149994,
    "low": 126.32,
    "close": 127.120003,
    "adjClose": 127.120003,
    "volume": 62377600
  },
  {
    "date": "2023-10-02",
    "open": 127.279999,
    "high": 130.470001,
    "low": 126.540001,
    "close": 129.460007,
    "adjClose": 129.460007,
    "volume": 48029700
  },
  {
    "date": "2023-10-03",
    "open": 128.059998,
    "high": 128.520004,
    "low": 124.25,
    "close": 124.720001,
    "adjClose": 124.720001,
    "volume": 51565000
  },
  {
    "date": "2023-10-04",
    "open": 126.059998,
    "high": 127.360001,
    "low": 125.68,
    "close": 127.0,
    "adjClose": 127.0,
    "volume": 44203900
  },
  {
    "date": "2023-10-05",
    "open": 126.709999,
    "high": 126.730003,
    "low": 124.330002,
    "close": 125.959999,
    "adjClose": 125.959999,
    "volume": 39660600
  },
  {
    "date": "2023-10-06",
    "open": 124.160004,
    "high": 128.449997,
    "low": 124.129997,
    "close": 127.959999,
    "adjClose": 127.959999,
    "volume": 46795900
  },
  {
    "date": "2023-10-09",
    "open": 126.220001,
    "high": 128.789993,
    "low": 124.760002,
    "close": 128.259995,
    "adjClose": 128.259995,
    "volume": 38773700
  },
  {
    "date": "2023-10-10",
    "open": 128.820007,
    "high": 130.740005,
    "low": 128.050003,
    "close": 129.479996,
    "adjClose": 129.479996,
    "volume": 42178600
  },
  {
    "date": "2023-10-11",
    "open": 129.740005,
    "high": 132.050003,
    "low": 129.610001,
    "close": 131.830002,
    "adjClose": 131.830002,
    "volume": 40741800
  },
  {
    "date": "2023-10-12",
    "open": 132.169998,
    "high": 134.479996,
    "low": 131.229996,
    "close": 132.330002,
    "adjClose": 132.330002,
    "volume": 55528600
  },
  {
    "date": "2023-10-13",
    "open": 132.979996,
    "high": 133.309998,
    "low": 128.949997,
    "close": 129.789993,
    "adjClose": 129.789993,
    "volume": 45786600
  },
  {
    "date": "2023-10-16",
    "open": 130.690002,
    "high": 133.070007,
    "low": 130.429993,
    "close": 132.550003,
    "adjClose": 132.550003,
    "volume": 42832900
  },
  {
    "date": "2023-10-17",
    "open": 130.389999,
    "high": 132.580002,
    "low": 128.710007,
    "close": 131.470001,
    "adjClose": 131.470001,
    "volume": 49344600
  },
  {
    "date": "2023-10-18",
    "open": 129.899994,
    "high": 130.669998,
    "low": 127.510002,
    "close": 128.130005,
    "adjClose": 128.130005,
    "volume": 42699500
  },
  {
    "date": "2023-10-19",
    "open": 130.570007,
    "high": 132.240005,
    "low": 127.470001,
    "close": 128.399994,
    "adjClose": 128.399994,
    "volume": 60961400
  },
  {
    "date": "2023-10-20",
    "open": 128.050003,
    "high": 128.169998,
    "low": 124.970001,
    "close": 125.169998,
    "adjClose": 125.169998,
    "volume": 56343300
  },
  {
    "date": "2023-10-23",
    "open": 124.629997,
    "high": 127.879997,
    "low": 123.980003,
    "close": 126.559998,
    "adjClose": 126.559998,
    "volume": 48260000
  },
  {
    "date": "2023-10-24",
    "open": 127.739998,
    "high": 128.800003,
    "low": 126.339996,
    "close": 128.559998,
    "adjClose": 128.559998,
    "volume": 46477400
  },
  {
    "date": "2023-10-25",
    "open": 126.040001,
    "high": 126.339996,
    "low": 120.790001,
    "close": 121.389999,
    "adjClose": 121.389999,
    "volume": 74577500
  },
  {
    "date": "2023-10-26",
    "open": 120.629997,
    "high": 121.639999,
    "low": 118.349998,
    "close": 119.57,
    "adjClose": 119.57,
    "volume": 100419500
  },
  {
    "date": "2023-10-27",
    "open": 126.199997,
    "high": 130.020004,
    "low": 125.519997,
    "close": 127.739998,
    "adjClose": 127.739998,
    "volume": 125309300
  },
  {
    "date": "2023-10-30",
    "open": 129.720001,
    "high": 133.0,
    "low": 128.559998,
    "close": 132.710007,
    "adjClose": 132.710007,
    "volume": 72485500
  },
  {
    "date": "2023-10-31",
    "open": 132.75,
    "high": 133.570007,
    "low": 131.710007,
    "close": 133.089996,
    "adjClose": 133.089996,
    "volume": 51589400
  },
  {
    "date": "2023-11-01",
    "open": 133.960007,
    "high": 137.350006,
    "low": 133.710007,
    "close": 137.0,
    "adjClose": 137.0,
    "volume": 61529400
  },
  {
    "date": "2023-11-02",
    "open": 138.729996,
    "high": 138.809998,
    "low": 136.470001,
    "close": 138.070007,
    "adjClose": 138.070007,
    "volume": 52236700
  },
  {
    "date": "2023-11-03",
    "open": 138.990005,
    "high": 139.490005,
    "low": 137.449997,
    "close": 138.600006,
    "adjClose": 138.600006,
    "volume": 44007200
  },
  {
    "date": "2023-11-06",
    "open": 138.759995,
    "high": 140.729996,
    "low": 138.360001,
    "close": 139.740005,
    "adjClose": 139.740005,
    "volume": 44970400
  },
  {
    "date": "2023-11-07",
    "open": 140.550003,
    "high": 143.369995,
    "low": 140.5,
    "close": 142.710007,
    "adjClose": 142.710007,
    "volume": 53553500
  },
  {
    "date": "2023-11-08",
    "open": 142.970001,
    "high": 143.119995,
    "low": 141.220001,
    "close": 142.080002,
    "adjClose": 142.080002,
    "volume": 44521700
  },
  {
    "date": "2023-11-09",
    "open": 142.020004,
    "high": 142.649994,
    "low": 139.839996,
    "close": 140.600006,
    "adjClose": 140.600006,
    "volume": 36235400
  },
  {
    "date": "2023-11-10",
    "open": 140.460007,
    "high": 143.649994,
    "low": 139.910004,
    "close": 143.559998,
    "adjClose": 143.559998,
    "volume": 49287800
  },
  {
    "date": "2023-11-13",
    "open": 142.080002,
    "high": 143.229996,
    "low": 140.669998,
    "close": 142.589996,
    "adjClose": 142.589996,
    "volume": 35680600
  },
  {
    "date": "2023-11-14",
    "open": 145.0,
    "high": 147.259995,
    "low": 144.679993,
    "close": 145.800003,
    "adjClose": 145.800003,
    "volume": 56674600
  },
  {
    "date": "2023-11-15",
    "open": 147.059998,
    "high": 147.289993,
    "low": 142.589996,
    "close": 143.199997,
    "adjClose": 143.199997,
    "volume": 63875700
  },
  {
    "date": "2023-11-16",
    "open": 140.910004,
    "high": 143.320007,
    "low": 139.520004,
    "close": 142.830002,
    "adjClose": 142.830002,
    "volume": 49653500
  },
  {
    "date": "2023-11-17",
    "open": 142.660004,
    "high": 145.229996,
    "low": 142.539993,
    "close": 145.179993,
    "adjClose": 145.179993,
    "volume": 49636700
  },
  {
    "date": "2023-11-20",
    "open": 145.130005,
    "high": 146.630005,
    "low": 144.729996,
    "close": 146.130005,
    "adjClose": 146.130005,
    "volume": 41951200
  },
  {
    "date": "2023-11-21",
    "open": 143.910004,
    "high": 144.050003,
    "low": 141.5,
    "close": 143.899994,
    "adjClose": 143.899994,
    "volume": 71226000
  },
  {
    "date": "2023-11-22",
    "open": 144.570007,
    "high": 147.740005,
    "low": 144.570007,
    "close": 146.710007,
    "adjClose": 146.710007,
    "volume": 45669100
  },
  {
    "date": "2023-11-24",
    "open": 146.699997,
    "high": 147.199997,
    "low": 145.320007,
    "close": 146.740005,
    "adjClose": 146.740005,
    "volume": 22378400
  },
  {
    "date": "2023-11-27",
    "open": 147.529999,
    "high": 149.259995,
    "low": 146.880005,
    "close": 147.729996,
    "adjClose": 147.729996,
    "volume": 53762400
  },
  {
    "date": "2023-11-28",
    "open": 146.979996,
    "high": 147.600006,
    "low": 145.529999,
    "close": 147.029999,
    "adjClose": 147.029999,
    "volume": 42711700
  },
  {
    "date": "2023-11-29",
    "open": 147.850006,
    "high": 148.539993,
    "low": 145.970001,
    "close": 146.320007,
    "adjClose": 146.320007,
    "volume": 40610900
  },
  {
    "date": "2023-11-30",
    "open": 144.759995,
    "high": 146.929993,
    "low": 144.330002,
    "close": 146.089996,
    "adjClose": 146.089996,
    "volume": 65814000
  },
  {
    "date": "2023-12-01",
    "open": 146.0,
    "high": 147.25,
    "low": 145.550003,
    "close": 147.029999,
    "adjClose": 147.029999,
    "volume": 39924600
  },
  {
    "date": "2023-12-04",
    "open": 145.25,
    "high": 145.350006,
    "low": 142.809998,
    "close": 144.839996,
    "adjClose": 144.839996,
    "volume": 48294200
  },
  {
    "date": "2023-12-05",
    "open": 143.550003,
    "high": 148.570007,
    "low": 143.130005,
    "close": 146.880005,
    "adjClose": 146.880005,
    "volume": 46822400
  },
  {
    "date": "2023-12-06",
    "open": 147.580002,
    "high": 147.850006,
    "low": 144.279999,
    "close": 144.520004,
    "adjClose": 144.520004,
    "volume": 39679000
  },
  {
    "date": "2023-12-07",
    "open": 146.149994,
    "high": 147.919998,
    "low": 145.339996,
    "close": 146.880005,
    "adjClose": 146.880005,
    "volume": 52352800
  },
  {
    "date": "2023-12-08",
    "open": 145.479996,
    "high": 147.839996,
    "low": 145.399994,
    "close": 147.419998,
    "adjClose": 147.419998,
    "volume": 41858000
  },
  {
    "date": "2023-12-11",
    "open": 145.660004,
    "high": 146.190002,
    "low": 143.639999,
    "close": 145.889999,
    "adjClose": 145.889999,
    "volume": 50907300
  },
  {
    "date": "2023-12-12",
    "open": 145.520004,
    "high": 147.5,
    "low": 145.300003,
    "close": 147.479996,
    "adjClose": 147.479996,
    "volume": 44944300
  },
  {
    "date": "2023-12-13",
    "open": 148.119995,
    "high": 149.460007,
    "low": 146.820007,
    "close": 148.839996,
    "adjClose": 148.839996,
    "volume": 52766200
  },
  {
    "date": "2023-12-14",
    "open": 149.929993,
    "high": 150.539993,
    "low": 145.520004,
    "close": 147.419998,
    "adjClose": 147.419998,
    "volume": 58400800
  },
  {
    "date": "2023-12-15",
    "open": 148.380005,
    "high": 150.570007,
    "low": 147.880005,
    "close": 149.970001,
    "adjClose": 149.970001,
    "volume": 110039100
  },
  {
    "date": "2023-12-18",
    "open": 150.559998,
    "high": 154.850006,
    "low": 150.050003,
    "close": 154.070007,
    "adjClose": 154.070007,
    "volume": 62512800
  },
  {
    "date": "2023-12-19",
    "open": 154.399994,
    "high": 155.119995,
    "low": 152.690002,
    "close": 153.789993,
    "adjClose": 153.789993,
    "volume": 43171300
  },
  {
    "date": "2023-12-20",
    "open": 152.899994,
    "high": 155.630005,
    "low": 151.559998,
    "close": 152.119995,
    "adjClose": 152.119995,
    "volume": 50322100
  },
  {
    "date": "2023-12-21",
    "open": 153.300003,
    "high": 153.970001,
    "low": 152.100006,
    "close": 153.839996,
    "adjClose": 153.839996,
    "volume": 36305700
  },
  {
    "date": "2023-12-22",
    "open": 153.770004,
    "high": 154.350006,
    "low": 152.710007,
    "close": 153.419998,
    "adjClose": 153.419998,
    "volume": 29480100
  },
  {
    "date": "2023-12-26",
    "open": 153.559998,
    "high": 153.979996,
    "low": 153.029999,
    "close": 153.410004,
    "adjClose": 153.410004,
    "volume": 25067200
  },
  {
    "date": "2023-12-27",
    "open": 153.559998,
    "high": 154.779999,
    "low": 153.119995,
    "close": 153.339996,
    "adjClose": 153.339996,
    "volume": 31434700
  },
  {
    "date": "2023-12-28",
    "open": 153.720001,
    "high": 154.080002,
    "low": 152.949997,
    "close": 153.380005,
    "adjClose": 153.380005,
    "volume": 27057000
  },
  {
    "date": "2023-12-29",
    "open": 153.100006,
    "high": 153.889999,
    "low": 151.029999,
    "close": 151.940002,
    "adjClose": 151.940002,
    "volume": 39789000
  },
  {
    "date": "2024-01-02",
    "open": 151.539993,
    "high": 152.380005,
    "low": 148.389999,
    "close": 149.929993,
    "adjClose": 149.929993,
    "volume": 47339400
  },
  {
    "date": "2024-01-03",
    "open": 149.199997,
    "high": 151.050003,
    "low": 148.330002,
    "close": 148.470001,
    "adjClose": 148.470001,
    "volume": 49425500
  },
  {
    "date": "2024-01-04",
    "open": 145.589996,
    "high": 147.380005,
    "low": 144.050003,
    "close": 144.570007,
    "adjClose": 144.570007,
    "volume": 56039800
  },
  {
    "date": "2024-01-05",
    "open": 144.690002,
    "high": 146.589996,
    "low": 144.529999,
    "close": 145.240005,
    "adjClose": 145.240005,
    "volume": 45124800
  },
  {
    "date": "2024-01-08",
    "open": 146.740005,
    "high": 149.399994,
    "low": 146.149994,
    "close": 149.100006,
    "adjClose": 149.100006,
    "volume": 46757100
  },
  {
    "date": "2024-01-09",
    "open": 148.330002,
    "high": 151.710007,
    "low": 148.210007,
    "close": 151.369995,
    "adjClose": 151.369995,
    "volume": 43812600
  },
  {
    "date": "2024-01-10",
    "open": 152.059998,
    "high": 154.419998,
    "low": 151.880005,
    "close": 153.729996,
    "adjClose": 153.729996,
    "volume": 44421800
  },
  {
    "date": "2024-01-11",
    "open": 155.039993,
    "high": 157.169998,
    "low": 153.119995,
    "close": 155.179993,
    "adjClose": 155.179993,
    "volume": 49072700
  },
  {
    "date": "2024-01-12",
    "open": 155.389999,
    "high": 156.199997,
    "low": 154.009995,
    "close": 154.619995,
    "adjClose": 154.619995,
    "volume": 40460300
  },
  {
    "date": "2024-01-16",
    "open": 153.529999,
    "high": 154.990005,
    "low": 152.149994,
    "close": 153.160004,
    "adjClose": 153.160004,
    "volume": 41384600
  },
  {
    "date": "2024-01-17",
    "open": 151.490005,
    "high": 152.149994,
    "low": 149.910004,
    "close": 151.710007,
    "adjClose": 151.710007,
    "volume": 34953400
  },
  {
    "date": "2024-01-18",
    "open": 152.770004,
    "high": 153.779999,
    "low": 151.820007,
    "close": 153.5,
    "adjClose": 153.5,
    "volume": 37850200
  },
  {
    "date": "2024-01-19",
    "open": 153.830002,
    "high": 155.759995,
    "low": 152.740005,
    "close": 155.339996,
    "adjClose": 155.339996,
    "volume": 51033700
  },
  {
    "date": "2024-01-22",
    "open": 156.889999,
    "high": 157.050003,
    "low": 153.899994,
    "close": 154.779999,
    "adjClose": 154.779999,
    "volume": 43687500
  },
  {
    "date": "2024-01-23",
    "open": 154.850006,
    "high": 156.210007,
    "low": 153.929993,
    "close": 156.020004,
    "adjClose": 156.020004,
    "volume": 37986000
  },
  {
    "date": "2024-01-24",
    "open": 157.800003,
    "high": 158.509995,
    "low": 156.479996,
    "close": 156.869995,
    "adjClose": 156.869995,
    "volume": 48547300
  },
  {
    "date": "2024-01-25",
    "open": 156.949997,
    "high": 158.509995,
    "low": 154.550003,
    "close": 157.75,
    "adjClose": 157.75,
    "volume": 43638600
  },
  {
    "date": "2024-01-26",
    "open": 158.419998,
    "high": 160.720001,
    "low": 157.910004,
    "close": 159.119995,
    "adjClose": 159.119995,
    "volume": 51047400
  },
  {
    "date": "2024-01-29",
    "open": 159.339996,
    "high": 161.289993,
    "low": 158.899994,
    "close": 161.259995,
    "adjClose": 161.259995,
    "volume": 45270400
  },
  {
    "date": "2024-01-30",
    "open": 160.699997,
    "high": 161.729996,
    "low": 158.490005,
    "close": 159.0,
    "adjClose": 159.0,
    "volume": 45207400
  },
  {
    "date": "2024-01-31",
    "open": 157.0,
    "high": 159.009995,
    "low": 154.809998,
    "close": 155.199997,
    "adjClose": 155.199997,
    "volume": 50284400
  },
  {
    "date": "2024-02-01",
    "open": 155.869995,
    "high": 159.759995,
    "low": 155.619995,
    "close": 159.279999,
    "adjClose": 159.279999,
    "volume": 76542400
  },
  {
    "date": "2024-02-02",
    "open": 169.190002,
    "high": 172.5,
    "low": 167.330002,
    "close": 171.809998,
    "adjClose": 171.809998,
    "volume": 117154900
  },
  {
    "date": "2024-02-05",
    "open": 170.199997,
    "high": 170.550003,
    "low": 167.699997,
    "close": 170.309998,
    "adjClose": 170.309998,
    "volume": 55081300
  },
  {
    "date": "2024-02-06",
    "open": 169.389999,
    "high": 170.710007,
    "low": 167.649994,
    "close": 169.149994,
    "adjClose": 169.149994,
    "volume": 42505500
  },
  {
    "date": "2024-02-07",
    "open": 169.479996,
    "high": 170.880005,
    "low": 168.940002,
    "close": 170.529999,
    "adjClose": 170.529999,
    "volume": 47174100
  },
  {
    "date": "2024-02-08",
    "open": 169.649994,
    "high": 171.429993,
    "low": 168.880005,
    "close": 169.839996,
    "adjClose": 169.839996,
    "volume": 42316500
  },
  {
    "date": "2024-02-09",
    "open": 170.899994,
    "high": 175.0,
    "low": 170.580002,
    "close": 174.449997,
    "adjClose": 174.449997,
    "volume": 56986000
  },
  {
    "date": "2024-02-12",
    "open": 174.800003,
    "high": 175.389999,
    "low": 171.539993,
    "close": 172.339996,
    "adjClose": 172.339996,
    "volume": 51050400
  },
  {
    "date": "2024-02-13",
    "open": 167.729996,
    "high": 170.949997,
    "low": 165.75,
    "close": 168.639999,
    "adjClose": 168.639999,
    "volume": 56345100
  },
  {
    "date": "2024-02-14",
    "open": 169.210007,
    "high": 171.210007,
    "low": 168.279999,
    "close": 170.979996,
    "adjClose": 170.979996,
    "volume": 42815500
  },
  {
    "date": "2024-02-15",
    "open": 170.580002,
    "high": 171.169998,
    "low": 167.589996,
    "close": 169.800003,
    "adjClose": 169.800003,
    "volume": 49855200
  },
  {
    "date": "2024-02-16",
    "open": 168.740005,
    "high": 170.419998,
    "low": 167.169998,
    "close": 169.509995,
    "adjClose": 169.509995,
    "volume": 48074600
  },
  {
    "date": "2024-02-20",
    "open": 167.830002,
    "high": 168.710007,
    "low": 165.740005,
    "close": 167.080002,
    "adjClose": 167.080002,
    "volume": 41980300
  },
  {
    "date": "2024-02-21",
    "open": 168.940002,
    "high": 170.229996,
    "low": 167.139999,
    "close": 168.589996,
    "adjClose": 168.589996,
    "volume": 44575600
  },
  {
    "date": "2024-02-22",
    "open": 173.100006,
    "high": 174.800003,
    "low": 171.770004,
    "close": 174.580002,
    "adjClose": 174.580002,
    "volume": 55392400
  },
  {
    "date": "2024-02-23",
    "open": 174.279999,
    "high": 175.75,
    "low": 173.699997,
    "close": 174.990005,
    "adjClose": 174.990005,
    "volume": 59715200
  },
  {
    "date": "2024-02-26",
    "open": 175.699997,
    "high": 176.369995,
    "low": 174.259995,
    "close": 174.729996,
    "adjClose": 174.729996,
    "volume": 44368600
  },
  {
    "date": "2024-02-27",
    "open": 174.080002,
    "high": 174.619995,
    "low": 172.860001,
    "close": 173.539993,
    "adjClose": 173.539993,
    "volume": 31141700
  },
  {
    "date": "2024-02-28",
    "open": 172.440002,
    "high": 174.050003,
    "low": 172.270004,
    "close": 173.160004,
    "adjClose": 173.160004,
    "volume": 28180500
  },
  {
    "date": "2024-02-29",
    "open": 173.009995,
    "high": 177.220001,
    "low": 172.850006,
    "close": 176.759995,
    "adjClose": 176.759995,
    "volume": 53805400
  },
  {
    "date": "2024-03-01",
    "open": 176.75,
    "high": 178.729996,
    "low": 176.070007,
    "close": 178.220001,
    "adjClose": 178.220001,
    "volume": 31956200
  },
  {
    "date": "2024-03-04",
    "open": 177.529999,
    "high": 180.139999,
    "low": 177.490005,
    "close": 177.580002,
    "adjClose": 177.580002,
    "volume": 37381500
  },
  {
    "date": "2024-03-05",
    "open": 176.929993,
    "high": 176.929993,
    "low": 173.300003,
    "close": 174.119995,
    "adjClose": 174.119995,
    "volume": 37228300
  },
  {
    "date": "2024-03-06",
    "open": 175.539993,
    "high": 176.460007,
    "low": 173.259995,
    "close": 173.509995,
    "adjClose": 173.509995,
    "volume": 32090900
  },
  {
    "date": "2024-03-07",
    "open": 174.830002,
    "high": 177.990005,
    "low": 173.720001,
    "close": 176.820007,
    "adjClose": 176.820007,
    "volume": 34063300
  },
  {
    "date": "2024-03-08",
    "open": 176.440002,
    "high": 178.789993,
    "low": 174.330002,
    "close": 175.350006,
    "adjClose": 175.350006,
    "volume": 37853500
  },
  {
    "date": "2024-03-11",
    "open": 174.309998,
    "high": 174.470001,
    "low": 171.470001,
    "close": 171.960007,
    "adjClose": 171.960007,
    "volume": 28484800
  },
  {
    "date": "2024-03-12",
    "open": 173.5,
    "high": 176.759995,
    "low": 171.979996,
    "close": 175.389999,
    "adjClose": 175.389999,
    "volume": 36610600
  },
  {
    "date": "2024-03-13",
    "open": 175.899994,
    "high": 177.619995,
    "low": 175.550003,
    "close": 176.559998,
    "adjClose": 176.559998,
    "volume": 30772600
  },
  {
    "date": "2024-03-14",
    "open": 177.690002,
    "high": 179.529999,
    "low": 176.470001,
    "close": 178.75,
    "adjClose": 178.75,
    "volume": 43705800
  },
  {
    "date": "2024-03-15",
    "open": 176.639999,
    "high": 177.929993,
    "low": 173.899994,
    "close": 174.419998,
    "adjClose": 174.419998,
    "volume": 72115500
  },
  {
    "date": "2024-03-18",
    "open": 175.800003,
    "high": 176.690002,
    "low": 174.279999,
    "close": 174.479996,
    "adjClose": 174.479996,
    "volume": 31250700
  },
  {
    "date": "2024-03-19",
    "open": 174.220001,
    "high": 176.089996,
    "low": 173.520004,
    "close": 175.899994,
    "adjClose": 175.899994,
    "volume": 26880900
  },
  {
    "date": "2024-03-20",
    "open": 176.139999,
    "high": 178.529999,
    "low": 174.639999,
    "close": 178.149994,
    "adjClose": 178.149994,
    "volume": 29947200
  },
  {
    "date": "2024-03-21",
    "open": 179.990005,
    "high": 181.419998,
    "low": 178.149994,
    "close": 178.149994,
    "adjClose": 178.149994,
    "volume": 32824300
  },
  {
    "date": "2024-03-22",
    "open": 177.75,
    "high": 179.259995,
    "low": 176.75,
    "close": 178.869995,
    "adjClose": 178.869995,
    "volume": 27964100
  },
  {
    "date": "2024-03-25",
    "open": 178.009995,
    "high": 180.990005,
    "low": 177.240005,
    "close": 179.710007,
    "adjClose": 179.710007,
    "volume": 29815500
  },
  {
    "date": "2024-03-26",
    "open": 180.149994,
    "high": 180.449997,
    "low": 177.949997,
    "close": 178.300003,
    "adjClose": 178.300003,
    "volume": 29659000
  },
  {
    "date": "2024-03-27",
    "open": 179.880005,
    "high": 180.0,
    "low": 177.309998,
    "close": 179.830002,
    "adjClose": 179.830002,
    "volume": 33272600
  },
  {
    "date": "2024-03-28",
    "open": 180.169998,
    "high": 181.699997,
    "low": 179.259995,
    "close": 180.380005,
    "adjClose": 180.380005,
    "volume": 38051600
  },
  {
    "date": "2024-04-01",
    "open": 180.789993,
    "high": 183.0,
    "low": 179.949997,
    "close": 180.970001,
    "adjClose": 180.970001,
    "volume": 29174500
  },
  {
    "date": "2024-04-02",
    "open": 179.070007,
    "high": 180.789993,
    "low": 178.380005,
    "close": 180.690002,
    "adjClose": 180.690002,
    "volume": 32611500
  },
  {
    "date": "2024-04-03",
    "open": 179.899994,
    "high": 182.869995,
    "low": 179.800003,
    "close": 182.410004,
    "adjClose": 182.410004,
    "volume": 31046600
  },
  {
    "date": "2024-04-04",
    "open": 184.0,
    "high": 185.100006,
    "low": 180.0,
    "close": 180.0,
    "adjClose": 180.0,
    "volume": 41624300
  },
  {
    "date": "2024-04-05",
    "open": 182.380005,
    "high": 186.270004,
    "low": 181.970001,
    "close": 185.070007,
    "adjClose": 185.070007,
    "volume": 42335200
  },
  {
    "date": "2024-04-08",
    "open": 186.899994,
    "high": 187.289993,
    "low": 184.809998,
    "close": 185.190002,
    "adjClose": 185.190002,
    "volume": 39221300
  },
  {
    "date": "2024-04-09",
    "open": 187.240005,
    "high": 187.339996,
    "low": 184.199997,
    "close": 185.669998,
    "adjClose": 185.669998,
    "volume": 36546900
  },
  {
    "date": "2024-04-10",
    "open": 182.770004,
    "high": 186.270004,
    "low": 182.669998,
    "close": 185.949997,
    "adjClose": 185.949997,
    "volume": 35879200
  },
  {
    "date": "2024-04-11",
    "open": 186.740005,
    "high": 189.770004,
    "low": 185.509995,
    "close": 189.050003,
    "adjClose": 189.050003,
    "volume": 40020700
  },
  {
    "date": "2024-04-12",
    "open": 187.720001,
    "high": 188.380005,
    "low": 185.080002,
    "close": 186.130005,
    "adjClose": 186.130005,
    "volume": 38554300
  },
  {
    "date": "2024-04-15",
    "open": 187.429993,
    "high": 188.690002,
    "low": 183.0,
    "close": 183.619995,
    "adjClose": 183.619995,
    "volume": 48052400
  },
  {
    "date": "2024-04-16",
    "open": 183.270004,
    "high": 184.830002,
    "low": 182.259995,
    "close": 183.320007,
    "adjClose": 183.320007,
    "volume": 32891300
  },
  {
    "date": "2024-04-17",
    "open": 184.309998,
    "high": 184.570007,
    "low": 179.820007,
    "close": 181.279999,
    "adjClose": 181.279999,
    "volume": 31359700
  },
  {
    "date": "2024-04-18",
    "open": 181.470001,
    "high": 182.389999,
    "low": 178.649994,
    "close": 179.220001,
    "adjClose": 179.220001,
    "volume": 30723800
  },
  {
    "date": "2024-04-19",
    "open": 178.740005,
    "high": 179.0,
    "low": 173.440002,
    "close": 174.630005,
    "adjClose": 174.630005,
    "volume": 55950000
  },
  {
    "date": "2024-04-22",
    "open": 176.940002,
    "high": 178.869995,
    "low": 174.559998,
    "close": 177.229996,
    "adjClose": 177.229996,
    "volume": 37924900
  },
  {
    "date": "2024-04-23",
    "open": 178.080002,
    "high": 179.929993,
    "low": 175.979996,
    "close": 179.539993,
    "adjClose": 179.539993,
    "volume": 37046500
  },
  {
    "date": "2024-04-24",
    "open": 179.940002,
    "high": 180.320007,
    "low": 176.179993,
    "close": 176.589996,
    "adjClose": 176.589996,
    "volume": 34185100
  },
  {
    "date": "2024-04-25",
    "open": 169.679993,
    "high": 173.919998,
    "low": 166.320007,
    "close": 173.669998,
    "adjClose": 173.669998,
    "volume": 49249400
  },
  {
    "date": "2024-04-26",
    "open": 177.800003,
    "high": 180.820007,
    "low": 176.130005,
    "close": 179.619995,
    "adjClose": 179.619995,
    "volume": 43919800
  },
  {
    "date": "2024-04-29",
    "open": 182.75,
    "high": 183.529999,
    "low": 179.389999,
    "close": 180.960007,
    "adjClose": 180.960007,
    "volume": 54063900
  },
  {
    "date": "2024-04-30",
    "open": 181.089996,
    "high": 182.990005,
    "low": 174.800003,
    "close": 175.0,
    "adjClose": 175.0,
    "volume": 94639800
  },
  {
    "date": "2024-05-01",
    "open": 181.639999,
    "high": 185.149994,
    "low": 176.559998,
    "close": 179.0,
    "adjClose": 179.0,
    "volume": 94645100
  },
  {
    "date": "2024-05-02",
    "open": 180.850006,
    "high": 185.100006,
    "low": 179.910004,
    "close": 184.720001,
    "adjClose": 184.720001,
    "volume": 54303500
  },
  {
    "date": "2024-05-03",
    "open": 186.990005,
    "high": 187.869995,
    "low": 185.419998,
    "close": 186.210007,
    "adjClose": 186.210007,
    "volume": 39172000
  },
  {
    "date": "2024-05-06",
    "open": 186.279999,
    "high": 188.75,
    "low": 184.800003,
    "close": 188.699997,
    "adjClose": 188.699997,
    "volume": 34725300
  },
  {
    "date": "2024-05-07",
    "open": 188.919998,
    "high": 189.940002,
    "low": 187.309998,
    "close": 188.759995,
    "adjClose": 188.759995,
    "volume": 34048900
  },
  {
    "date": "2024-05-08",
    "open": 187.440002,
    "high": 188.429993,
    "low": 186.389999,
    "close": 188.0,
    "adjClose": 188.0,
    "volume": 26136400
  },
  {
    "date": "2024-05-09",
    "open": 188.880005,
    "high": 191.699997,
    "low": 187.440002,
    "close": 189.5,
    "adjClose": 189.5,
    "volume": 43368400
  },
  {
    "date": "2024-05-10",
    "open": 189.160004,
    "high": 189.889999,
    "low": 186.929993,
    "close": 187.479996,
    "adjClose": 187.479996,
    "volume": 34141800
  },
  {
    "date": "2024-05-13",
    "open": 188.0,
    "high": 188.309998,
    "low": 185.360001,
    "close": 186.570007,
    "adjClose": 186.570007,
    "volume": 24898600
  },
  {
    "date": "2024-05-14",
    "open": 183.820007,
    "high": 187.720001,
    "low": 183.449997,
    "close": 187.070007,
    "adjClose": 187.070007,
    "volume": 38698200
  },
  {
    "date": "2024-05-15",
    "open": 185.970001,
    "high": 186.720001,
    "low": 182.729996,
    "close": 185.990005,
    "adjClose": 185.990005,
    "volume": 75459900
  },
  {
    "date": "2024-05-16",
    "open": 185.600006,
    "high": 187.309998,
    "low": 183.460007,
    "close": 183.630005,
    "adjClose": 183.630005,
    "volume": 38834500
  },
  {
    "date": "2024-05-17",
    "open": 183.759995,
    "high": 185.300003,
    "low": 183.350006,
    "close": 184.699997,
    "adjClose": 184.699997,
    "volume": 33175700
  },
  {
    "date": "2024-05-20",
    "open": 184.339996,
    "high": 186.669998,
    "low": 183.279999,
    "close": 183.539993,
    "adjClose": 183.539993,
    "volume": 30511800
  },
  {
    "date": "2024-05-21",
    "open": 182.300003,
    "high": 183.259995,
    "low": 180.75,
    "close": 183.149994,
    "adjClose": 183.149994,
    "volume": 50839100
  },
  {
    "date": "2024-05-22",
    "open": 183.880005,
    "high": 185.220001,
    "low": 181.970001,
    "close": 183.130005,
    "adjClose": 183.130005,
    "volume": 28148800
  },
  {
    "date": "2024-05-23",
    "open": 183.660004,
    "high": 184.759995,
    "low": 180.080002,
    "close": 181.050003,
    "adjClose": 181.050003,
    "volume": 33670200
  },
  {
    "date": "2024-05-24",
    "open": 181.649994,
    "high": 182.440002,
    "low": 180.300003,
    "close": 180.75,
    "adjClose": 180.75,
    "volume": 27434100
  },
  {
    "date": "2024-05-28",
    "open": 179.929993,
    "high": 182.240005,
    "low": 179.490005,
    "close": 182.149994,
    "adjClose": 182.149994,
    "volume": 29927000
  },
  {
    "date": "2024-05-29",
    "open": 181.699997,
    "high": 184.080002,
    "low": 181.550003,
    "close": 182.020004,
    "adjClose": 182.020004,
    "volume": 32009300
  },
  {
    "date": "2024-05-30",
    "open": 181.309998,
    "high": 181.339996,
    "low": 178.360001,
    "close": 179.320007,
    "adjClose": 179.320007,
    "volume": 29249200
  },
  {
    "date": "2024-05-31",
    "open": 178.300003,
    "high": 179.210007,
    "low": 173.869995,
    "close": 176.440002,
    "adjClose": 176.440002,
    "volume": 58903900
  },
  {
    "date": "2024-06-03",
    "open": 177.699997,
    "high": 178.699997,
    "low": 175.919998,
    "close": 178.339996,
    "adjClose": 178.339996,
    "volume": 30786600
  },
  {
    "date": "2024-06-04",
    "open": 177.639999,
    "high": 179.820007,
    "low": 176.440002,
    "close": 179.339996,
    "adjClose": 179.339996,
    "volume": 27198400
  },
  {
    "date": "2024-06-05",
    "open": 180.100006,
    "high": 181.5,
    "low": 178.75,
    "close": 181.279999,
    "adjClose": 181.279999,
    "volume": 32116400
  },
  {
    "date": "2024-06-06",
    "open": 181.75,
    "high": 185.0,
    "low": 181.490005,
    "close": 185.0,
    "adjClose": 185.0,
    "volume": 31371200
  },
  {
    "date": "2024-06-07",
    "open": 184.899994,
    "high": 186.289993,
    "low": 183.360001,
    "close": 184.300003,
    "adjClose": 184.300003,
    "volume": 28021500
  },
  {
    "date": "2024-06-10",
    "open": 184.070007,
    "high": 187.229996,
    "low": 183.789993,
    "close": 187.059998,
    "adjClose": 187.059998,
    "volume": 34494500
  },
  {
    "date": "2024-06-11",
    "open": 187.059998,
    "high": 187.770004,
    "low": 184.539993,
    "close": 187.229996,
    "adjClose": 187.229996,
    "volume": 27265100
  },
  {
    "date": "2024-06-12",
    "open": 188.020004,
    "high": 188.350006,
    "low": 185.429993,
    "close": 186.889999,
    "adjClose": 186.889999,
    "volume": 33984200
  },
  {
    "date": "2024-06-13",
    "open": 186.089996,
    "high": 187.669998,
    "low": 182.669998,
    "close": 183.830002,
    "adjClose": 183.830002,
    "volume": 39721500
  },
  {
    "date": "2024-06-14",
    "open": 183.080002,
    "high": 183.720001,
    "low": 182.229996,
    "close": 183.660004,
    "adjClose": 183.660004,
    "volume": 25456400
  },
  {
    "date": "2024-06-17",
    "open": 182.520004,
    "high": 185.0,
    "low": 181.220001,
    "close": 184.059998,
    "adjClose": 184.059998,
    "volume": 35601900
  },
  {
    "date": "2024-06-18",
    "open": 183.740005,
    "high": 184.289993,
    "low": 181.429993,
    "close": 182.809998,
    "adjClose": 182.809998,
    "volume": 36659200
  },
  {
    "date": "2024-06-20",
    "open": 182.910004,
    "high": 186.509995,
    "low": 182.720001,
    "close": 186.100006,
    "adjClose": 186.100006,
    "volume": 44726800
  },
  {
    "date": "2024-06-21",
    "open": 187.800003,
    "high": 189.279999,
    "low": 185.860001,
    "close": 189.080002,
    "adjClose": 189.080002,
    "volume": 72931800
  },
  {
    "date": "2024-06-24",
    "open": 189.330002,
    "high": 191.0,
    "low": 185.330002,
    "close": 185.570007,
    "adjClose": 185.570007,
    "volume": 50610400
  },
  {
    "date": "2024-06-25",
    "open": 186.809998,
    "high": 188.839996,
    "low": 185.419998,
    "close": 186.339996,
    "adjClose": 186.339996,
    "volume": 45898500
  },
  {
    "date": "2024-06-26",
    "open": 186.919998,
    "high": 194.800003,
    "low": 186.259995,
    "close": 193.610001,
    "adjClose": 193.610001,
    "volume": 65103900
  },
  {
    "date": "2024-06-27",
    "open": 195.009995,
    "high": 199.839996,
    "low": 194.199997,
    "close": 197.850006,
    "adjClose": 197.850006,
    "volume": 74397500
  },
  {
    "date": "2024-06-28",
    "open": 197.729996,
    "high": 198.850006,
    "low": 192.5,
    "close": 193.25,
    "adjClose": 193.25,
    "volume": 76930200
  },
  {
    "date": "2024-07-01",
    "open": 193.490005,
    "high": 198.300003,
    "low": 192.820007,
    "close": 197.199997,
    "adjClose": 197.199997,
    "volume": 41192000
  },
  {
    "date": "2024-07-02",
    "open": 197.279999,
    "high": 200.429993,
    "low": 195.929993,
    "close": 200.0,
    "adjClose": 200.0,
    "volume": 45600000
  },
  {
    "date": "2024-07-03",
    "open": 199.940002,
    "high": 200.029999,
    "low": 196.759995,
    "close": 197.589996,
    "adjClose": 197.589996,
    "volume": 31597900
  },
  {
    "date": "2024-07-05",
    "open": 198.649994,
    "high": 200.550003,
    "low": 198.169998,
    "close": 200.0,
    "adjClose": 200.0,
    "volume": 39858900
  },
  {
    "date": "2024-07-08",
    "open": 200.039993,
    "high": 201.199997,
    "low": 197.960007,
    "close": 199.289993,
    "adjClose": 199.289993,
    "volume": 34767300
  },
  {
    "date": "2024-07-09",
    "open": 199.399994,
    "high": 200.570007,
    "low": 199.050003,
    "close": 199.339996,
    "adjClose": 199.339996,
    "volume": 32700100
  },
  {
    "date": "2024-07-10",
    "open": 200.0,
    "high": 200.110001,
    "low": 197.690002,
    "close": 199.789993,
    "adjClose": 199.789993,
    "volume": 32883800
  },
  {
    "date": "2024-07-11",
    "open": 200.089996,
    "high": 200.270004,
    "low": 192.860001,
    "close": 195.050003,
    "adjClose": 195.050003,
    "volume": 44565000
  },
  {
    "date": "2024-07-12",
    "open": 194.800003,
    "high": 196.470001,
    "low": 193.830002,
    "close": 194.490005,
    "adjClose": 194.490005,
    "volume": 30598500
  },
  {
    "date": "2024-07-15",
    "open": 194.559998,
    "high": 196.190002,
    "low": 190.830002,
    "close": 192.720001,
    "adjClose": 192.720001,
    "volume": 40683200
  },
  {
    "date": "2024-07-16",
    "open": 195.589996,
    "high": 196.619995,
    "low": 192.240005,
    "close": 193.020004,
    "adjClose": 193.020004,
    "volume": 33994700
  },
  {
    "date": "2024-07-17",
    "open": 191.350006,
    "high": 191.580002,
    "low": 185.990005,
    "close": 187.929993,
    "adjClose": 187.929993,
    "volume": 48076100
  },
  {
    "date": "2024-07-18",
    "open": 189.589996,
    "high": 189.679993,
    "low": 181.449997,
    "close": 183.75,
    "adjClose": 183.75,
    "volume": 51043600
  },
  {
    "date": "2024-07-19",
    "open": 181.139999,
    "high": 184.929993,
    "low": 180.110001,
    "close": 183.130005,
    "adjClose": 183.130005,
    "volume": 43081800
  },
  {
    "date": "2024-07-22",
    "open": 185.0,
    "high": 185.059998,
    "low": 182.479996,
    "close": 182.550003,
    "adjClose": 182.550003,
    "volume": 39874900
  }
]
