{
  "props": {
    "classes": {
      "type": { "name": "shape", "description": "Partial<ChatComposerClasses>" },
      "additionalInfo": { "cssApi": true }
    },
    "slotProps": { "type": { "name": "shape", "description": "ComposerToolbarSlotProps" } },
    "slots": {
      "type": { "name": "shape", "description": "Partial<ComposerToolbarSlots>" },
      "additionalInfo": { "slotsApi": true }
    }
  },
  "name": "ChatComposerToolbar",
  "imports": [
    "import { ChatComposerToolbar } from '@mui/x-chat/ChatComposer';",
    "import { ChatComposerToolbar } from '@mui/x-chat';"
  ],
  "slots": [{ "name": "toolbar", "description": "", "class": null }],
  "classes": [],
  "muiName": "MuiChatComposer",
  "filename": "/packages/x-chat/src/ChatComposer/ChatComposerToolbar.tsx",
  "inheritance": null,
  "demos": "<ul><li><a href=\"/x/react-chat/basics/composer/\">Chat - Composer</a></li></ul>",
  "cssComponent": false
}
