{
  "props": { "className": { "type": { "name": "string" } } },
  "name": "RadialBarPlot",
  "imports": [
    "import { RadialBarPlot } from '@mui/x-charts-premium/RadialBarChart';",
    "import { RadialBarPlot } from '@mui/x-charts-premium';"
  ],
  "classes": [],
  "muiName": "MuiRadialBarPlot",
  "filename": "/packages/x-charts-premium/src/RadialBarChart/RadialBarPlot.tsx",
  "inheritance": null,
  "demos": "<ul><li><a href=\"/x/react-charts/radial-bars/\">Charts - Radial Bars <a href=\"/x/introduction/licensing/#premium-plan\" title=\"Premium plan\"><span class=\"plan-premium\"></span></a> 🧪</a></li></ul>",
  "cssComponent": false
}
