{
  "name": "GridCsvExportApi",
  "description": "The CSV export API interface that is available in the grid [[apiRef]].",
  "properties": [
    {
      "name": "exportDataAsCsv",
      "description": "Downloads and exports a CSV of the grid's data.",
      "type": "(options?: { delimiter?: string, fileName?: string, utf8WithBom?: boolean, includeHeaders?: boolean, includeColumnGroupsHeaders?: boolean, getRowsToExport?: (params: { apiRef: RefObject<GridApiCommunity> }) => GridRowId[], shouldAppendQuotes?: boolean, escapeFormulas?: boolean, fields?: string[], allColumns?: boolean }) => void"
    },
    {
      "name": "getDataAsCsv",
      "description": "Returns the grid data as a CSV string.\nThis method is used internally by `exportDataAsCsv`.",
      "type": "(options?: { delimiter?: string, fileName?: string, utf8WithBom?: boolean, includeHeaders?: boolean, includeColumnGroupsHeaders?: boolean, getRowsToExport?: (params: { apiRef: RefObject<GridApiCommunity> }) => GridRowId[], shouldAppendQuotes?: boolean, escapeFormulas?: boolean, fields?: string[], allColumns?: boolean }) => string"
    }
  ]
}
